mlpype/base/__init__.py
mlpype/base/constants.py
mlpype/base/data/__init__.py
mlpype/base/data/data_catalog.py
mlpype/base/data/data_sink.py
mlpype/base/data/data_source.py
mlpype/base/data/dataset.py
mlpype/base/deploy/__init__.py
mlpype/base/deploy/inference.py
mlpype/base/deploy/wheel/__init__.py
mlpype/base/deploy/wheel/builder.py
mlpype/base/deploy/wheel/extensions.py
mlpype/base/deploy/wheel/helpers/setup_template.py
mlpype/base/deploy/wheel/helpers/wheel_main.py
mlpype/base/evaluate/__init__.py
mlpype/base/evaluate/base_evaluator.py
mlpype/base/evaluate/evaluator.py
mlpype/base/evaluate/plot.py
mlpype/base/experiment/__init__.py
mlpype/base/experiment/argument_parsing.py
mlpype/base/experiment/experiment.py
mlpype/base/logger/__init__.py
mlpype/base/logger/experiment_logger.py
mlpype/base/logger/local_logger.py
mlpype/base/model/__init__.py
mlpype/base/model/hierarchical_model.py
mlpype/base/model/model.py
mlpype/base/pipeline/__init__.py
mlpype/base/pipeline/operator.py
mlpype/base/pipeline/pipe.py
mlpype/base/pipeline/pipeline.py
mlpype/base/pipeline/type_checker.py
mlpype/base/serialiser/__init__.py
mlpype/base/serialiser/joblib_serialiser.py
mlpype/base/serialiser/serialiser.py
mlpype/base/utils/__init__.py
mlpype/base/utils/parsing.py
mlpype/base/utils/workspace.py
mlpype_base-0.6.12.dist-info/METADATA
mlpype_base-0.6.12.dist-info/WHEEL
mlpype_base-0.6.12.dist-info/RECORD
