Metadata-Version: 2.4
Name: mlpype-base
Version: 0.6.12
Summary: Base package for standardised machine learning
Author: Jeroen van den Hoven
License: MIT
Requires-Python: >=3.9
Requires-Dist: docstring-parser>=0.14.1
Requires-Dist: jinja2==3.1.6
Requires-Dist: joblib>=1.1.1
Requires-Dist: loguru>=0.7.3
Requires-Dist: pydantic>=1.10.7
Requires-Dist: pyyaml==6.0.1
Provides-Extra: strict
Requires-Dist: docstring-parser==0.14.1; extra == 'strict'
Requires-Dist: jinja2==3.1.6; extra == 'strict'
Requires-Dist: joblib==1.1.1; extra == 'strict'
Requires-Dist: pydantic==1.10.7; extra == 'strict'
Requires-Dist: pyyaml==6.0.1; extra == 'strict'
